adafruit_gps.py
adafruit_circuitpython_gps-3.11.4.dist-info/licenses/LICENSE
adafruit_circuitpython_gps-3.11.4.dist-info/METADATA
adafruit_circuitpython_gps-3.11.4.dist-info/WHEEL
adafruit_circuitpython_gps-3.11.4.dist-info/top_level.txt
adafruit_circuitpython_gps-3.11.4.dist-info/RECORD
