Metadata-Version: 2.4
Name: adafruit-circuitpython-gps
Version: 3.11.4
Summary: CircuitPython library for GPS modules.
Author-email: Adafruit Industries <circuitpython@adafruit.com>
License: MIT
Project-URL: Homepage, https://github.com/adafruit/Adafruit_CircuitPython_GPS
Keywords: adafruit,gps,module,latitude,longitude,breakout,hardware,micropython,circuitpython
Classifier: Intended Audience :: Developers
Classifier: Topic :: Software Development :: Libraries
Classifier: Topic :: Software Development :: Embedded Systems
Classifier: Topic :: System :: Hardware
Classifier: License :: OSI Approved :: MIT License
Classifier: Programming Language :: Python :: 3
License-File: LICENSE
Requires-Dist: Adafruit-Blinka
Requires-Dist: adafruit-circuitpython-busdevice
Requires-Dist: pyserial
Requires-Dist: adafruit-circuitpython-typing
Requires-Dist: typing-extensions~=4.0
Provides-Extra: optional
Requires-Dist: adafruit-circuitpython-sd; extra == "optional"
Requires-Dist: covdefaults; extra == "optional"
Requires-Dist: coverage; extra == "optional"
Requires-Dist: freezegun; extra == "optional"
Requires-Dist: pytest; extra == "optional"
Dynamic: license-file
